[
  {
    "movieName": "The Dark Knight",
    "watchTime": 152,
    "description": "Gotham's protector battles the Joker's chaos.",
    "poster": "https://c8.alamy.com/comp/C2WJYB/the-dark-knight-poster-display-at-the-arclight-theater-los-angeles-C2WJYB.jpg",
    "category": "Action/Crime",
    "imdbRating": 9.0,
    "id": "1221434hgd"
  },
  {
    "movieName": "The Shawshank Redemption",
    "watchTime": 142,
    "description": "Wrongfully imprisoned men bond over time.",
    "poster": "https://m.media-amazon.com/images/W/IMAGERENDERING_521856-T1/images/I/71JxA6I+sgL._AC_SL1000_.jpg",
    "category": "Drama",
    "imdbRating": 9.3,
    "id": "12214aa4hgd"
  },
  {
    "movieName": "Inception",
    "watchTime": 148,
    "description": "Dream thieves venture into a man's subconscious.",
    "poster": "https://irs.www.warnerbros.com/gallery-v2-jpeg/inception_posterlarge_0-587516945.jpg",
    "category": "Action/Sci-Fi",
    "imdbRating": 8.8,
    "id": "1okh1434hgd"
  },
  {
    "movieName": "Forrest Gump",
    "watchTime": 142,
    "description": "Simple man becomes unwitting participant in historic events.",
    "poster": "https://i.scdn.co/image/ab67616d0000b2737f570d8b2e794f1493dca2ca",
    "category": "Drama/Comedy",
    "imdbRating": 8.8,
    "id": "1221434h568gd"
  },
  {
    "movieName": "The Godfather",
    "watchTime": 175,
    "description": "Mafia family fights for control of organized crime.",
    "poster": "https://m.media-amazon.com/images/M/MV5BM2MyNjYxNmUtYTAwNi00MTYxLWJmNWYtYzZlODY3ZTk3OTFlXkEyXkFqcGdeQXVyNzkwMjQ5NzM@._V1_.jpg",
    "category": "Crime/Drama",
    "imdbRating": 9.2,
    "id": "1221434hahy11gd"
  }
]
